dynamic_upload_image_field/__init__.py
dynamic_upload_image_field/fields.py
dynamic_upload_image_field-0.1.2.dist-info/METADATA
dynamic_upload_image_field-0.1.2.dist-info/RECORD
dynamic_upload_image_field-0.1.2.dist-info/WHEEL
dynamic_upload_image_field-0.1.2.dist-info/top_level.txt
