Metadata-Version: 2.1
Name: dynamic-upload-image-field
Version: 0.1.2
Summary: A django ImageField that generates it's upload_to value from the model instance method get_upload_to.
Home-page: https://github.com/alexseitsinger/dynamic_upload_image_field
Author: Alex Seitsinger
Author-email: alexseitsinger@gmail.com
License: BSD 2-Clause License
Platform: UNKNOWN
Classifier: Development Status :: 3 - Alpha
Classifier: Intended Audience :: Developers
Classifier: Topic :: Utilities
Classifier: Programming Language :: Python
Classifier: Programming Language :: Python :: 3
Classifier: Programming Language :: Python :: 3.3
Classifier: Programming Language :: Python :: 3.4
Classifier: Programming Language :: Python :: 3.5
Classifier: Programming Language :: Python :: 3.6
Classifier: License :: OSI Approved :: BSD License
Requires-Dist: Django (>=2.0)
